mlprep/__init__.py
mlprep/clean.py
mlprep/preprocess.py
mlprep/utils.py
mlprep-0.0.3.dist-info/LICENSE
mlprep-0.0.3.dist-info/METADATA
mlprep-0.0.3.dist-info/WHEEL
mlprep-0.0.3.dist-info/top_level.txt
mlprep-0.0.3.dist-info/RECORD
