Metadata-Version: 2.1
Name: mlprep
Version: 0.0.3
Summary: A utility package for data preprocessing before the modelling exercise
Home-page: https://github.com/asanoop24/ml
Author: Anoop Sharma
Author-email: asanoop24@gmail.com
License: UNKNOWN
Platform: UNKNOWN
Classifier: Programming Language :: Python :: 3
Classifier: License :: OSI Approved :: MIT License
Classifier: Operating System :: OS Independent
Requires-Python: >=3.6
Requires-Dist: pandas
Requires-Dist: scikit-learn
